custom_module/__init__.py
custom_module/exceptions.py
custom_module/main.py
custom_module/utils.py
PackageBuilding-1.0.8.dist-info/METADATA
PackageBuilding-1.0.8.dist-info/WHEEL
PackageBuilding-1.0.8.dist-info/top_level.txt
PackageBuilding-1.0.8.dist-info/RECORD
