Metadata-Version: 2.1
Name: PackageBuilding
Version: 1.0.8
Summary: How to build the custom package in Python
Author: Krishna Belamkonda
Author-email: Krishna@gmail.com
License: MIT
Platform: Any
Requires-Python: >=3.8
